[
    [{
        "p": {
            "dimType": "GeographicDimension",
            "name": "province",
            "uk": "k2",
            "dimGranularity": "PROVINCE"
        },
        "t": "rowH",
        "v": "province"
    }, {
        "p": {
            "aggType": "sum",
            "dimType": "measureCol",
            "name": "price",
            "uk": "k0"
        },
        "t": "colH",
        "v": "price"
    }, {
        "p": {
            "aggType": "sum",
            "dimType": "measureCol",
            "name": "order_number",
            "uk": "k1"
        },
        "t": "colH",
        "v": "order_number-test1"
    }],
    [{
        "p": {
            "uk": "k2"
        },
        "t": "rowH",
        "v": "江苏"
    }, {
        "p": {
            "fmt": "#.00",
            "raw": "11708.11999999999"
        },
        "t": "data",
        "v": "11708.12"
    }, {
        "p": {
            "fmt": "#,##0",
            "raw": "3280.0"
        },
        "t": "data",
        "v": "3,280"
    }],
    [{
        "p": {
            "uk": "k2"
        },
        "t": "rowH",
        "v": "安徽"
    }, {
        "p": {
            "fmt": "#.00",
            "raw": "28061.34999999999"
        },
        "t": "data",
        "v": "28061.35"
    }, {
        "p": {
            "fmt": "#,##0",
            "raw": "7615.0"
        },
        "t": "data",
        "v": "7,615"
    }],
    [{
        "p": {
            "uk": "k2"
        },
        "t": "rowH",
        "v": "北京"
    }, {
        "p": {
            "fmt": "#.00",
            "raw": "32917.18"
        },
        "t": "data",
        "v": "32917.18"
    }, {
        "p": {
            "fmt": "#,##0",
            "raw": "8792.0"
        },
        "t": "data",
        "v": "8,792"
    }],
    [{
        "p": {
            "uk": "k2"
        },
        "t": "rowH",
        "v": "福建"
    }, {
        "p": {
            "fmt": "#.00",
            "raw": "9686.829999999996"
        },
        "t": "data",
        "v": "9686.83"
    }, {
        "p": {
            "fmt": "#,##0",
            "raw": "3006.0"
        },
        "t": "data",
        "v": "3,006"
    }],
    [{
        "p": {
            "uk": "k2"
        },
        "t": "rowH",
        "v": "甘肃"
    }, {
        "p": {
            "fmt": "#.00",
            "raw": "26736.25"
        },
        "t": "data",
        "v": "26736.25"
    }, {
        "p": {
            "fmt": "#,##0",
            "raw": "7891.0"
        },
        "t": "data",
        "v": "7,891"
    }],
    [{
        "p": {
            "uk": "k2"
        },
        "t": "rowH",
        "v": "广东"
    }, {
        "p": {
            "fmt": "#.00",
            "raw": "121927.89"
        },
        "t": "data",
        "v": "121927.89"
    }, {
        "p": {
            "fmt": "#,##0",
            "raw": "34233.0"
        },
        "t": "data",
        "v": "34,233"
    }],
    [{
        "p": {
            "uk": "k2"
        },
        "t": "rowH",
        "v": "广西"
    }, {
        "p": {
            "fmt": "#.00",
            "raw": "65910.30000000002"
        },
        "t": "data",
        "v": "65910.30"
    }, {
        "p": {
            "fmt": "#,##0",
            "raw": "19883.0"
        },
        "t": "data",
        "v": "19,883"
    }],
    [{
        "p": {
            "uk": "k2"
        },
        "t": "rowH",
        "v": "贵州"
    }, {
        "p": {
            "fmt": "#.00",
            "raw": "7991.789999999999"
        },
        "t": "data",
        "v": "7991.79"
    }, {
        "p": {
            "fmt": "#,##0",
            "raw": "1578.0"
        },
        "t": "data",
        "v": "1,578"
    }],
    [{
        "p": {
            "uk": "k2"
        },
        "t": "rowH",
        "v": "海南"
    }, {
        "p": {
            "fmt": "#.00",
            "raw": "31220.100000000017"
        },
        "t": "data",
        "v": "31220.10"
    }, {
        "p": {
            "fmt": "#,##0",
            "raw": "10115.0"
        },
        "t": "data",
        "v": "10,115"
    }],
    [{
        "p": {
            "uk": "k2"
        },
        "t": "rowH",
        "v": "河北"
    }, {
        "p": {
            "fmt": "#.00",
            "raw": "14689.439999999991"
        },
        "t": "data",
        "v": "14689.44"
    }, {
        "p": {
            "fmt": "#,##0",
            "raw": "4476.0"
        },
        "t": "data",
        "v": "4,476"
    }],
    [{
        "p": {
            "uk": "k2"
        },
        "t": "rowH",
        "v": "河南"
    }, {
        "p": {
            "fmt": "#.00",
            "raw": "31182.659999999985"
        },
        "t": "data",
        "v": "31182.66"
    }, {
        "p": {
            "fmt": "#,##0",
            "raw": "9413.0"
        },
        "t": "data",
        "v": "9,413"
    }],
    [{
        "p": {
            "uk": "k2"
        },
        "t": "rowH",
        "v": "黑龙江"
    }, {
        "p": {
            "fmt": "#.00",
            "raw": "21867.80000000001"
        },
        "t": "data",
        "v": "21867.80"
    }, {
        "p": {
            "fmt": "#,##0",
            "raw": "7271.0"
        },
        "t": "data",
        "v": "7,271"
    }],
    [{
        "p": {
            "uk": "k2"
        },
        "t": "rowH",
        "v": "湖北"
    }, {
        "p": {
            "fmt": "#.00",
            "raw": "15620.549999999997"
        },
        "t": "data",
        "v": "15620.55"
    }, {
        "p": {
            "fmt": "#,##0",
            "raw": "4856.0"
        },
        "t": "data",
        "v": "4,856"
    }],
    [{
        "p": {
            "uk": "k2"
        },
        "t": "rowH",
        "v": "湖南"
    }, {
        "p": {
            "fmt": "#.00",
            "raw": "10663.03"
        },
        "t": "data",
        "v": "10663.03"
    }, {
        "p": {
            "fmt": "#,##0",
            "raw": "4153.0"
        },
        "t": "data",
        "v": "4,153"
    }],
    [{
        "p": {
            "uk": "k2"
        },
        "t": "rowH",
        "v": "吉林"
    }, {
        "p": {
            "fmt": "#.00",
            "raw": "23911.57"
        },
        "t": "data",
        "v": "23911.57"
    }, {
        "p": {
            "fmt": "#,##0",
            "raw": "8637.0"
        },
        "t": "data",
        "v": "8,637"
    }],
    [{
        "p": {
            "uk": "k2"
        },
        "t": "rowH",
        "v": "江西"
    }, {
        "p": {
            "fmt": "#.00",
            "raw": "12983.01"
        },
        "t": "data",
        "v": "12983.01"
    }, {
        "p": {
            "fmt": "#,##0",
            "raw": "1927.0"
        },
        "t": "data",
        "v": "1,927"
    }],
    [{
        "p": {
            "uk": "k2"
        },
        "t": "rowH",
        "v": "辽宁"
    }, {
        "p": {
            "fmt": "#.00",
            "raw": "47037.86000000001"
        },
        "t": "data",
        "v": "47037.86"
    }, {
        "p": {
            "fmt": "#,##0",
            "raw": "16153.0"
        },
        "t": "data",
        "v": "16,153"
    }],
    [{
        "p": {
            "uk": "k2"
        },
        "t": "rowH",
        "v": "内蒙古"
    }, {
        "p": {
            "fmt": "#.00",
            "raw": "47967.85000000003"
        },
        "t": "data",
        "v": "47967.85"
    }, {
        "p": {
            "fmt": "#,##0",
            "raw": "11165.0"
        },
        "t": "data",
        "v": "11,165"
    }],
    [{
        "p": {
            "uk": "k2"
        },
        "t": "rowH",
        "v": "宁夏"
    }, {
        "p": {
            "fmt": "#.00",
            "raw": "6730.609999999998"
        },
        "t": "data",
        "v": "6730.61"
    }, {
        "p": {
            "fmt": "#,##0",
            "raw": "2458.0"
        },
        "t": "data",
        "v": "2,458"
    }],
    [{
        "p": {
            "uk": "k2"
        },
        "t": "rowH",
        "v": "青海"
    }, {
        "p": {
            "fmt": "#.00",
            "raw": "926.19"
        },
        "t": "data",
        "v": "926.19"
    }, {
        "p": {
            "fmt": "#,##0",
            "raw": "459.0"
        },
        "t": "data",
        "v": "459"
    }],
    [{
        "p": {
            "uk": "k2"
        },
        "t": "rowH",
        "v": "山东"
    }, {
        "p": {
            "fmt": "#.00",
            "raw": "18619.15"
        },
        "t": "data",
        "v": "18619.15"
    }, {
        "p": {
            "fmt": "#,##0",
            "raw": "4179.0"
        },
        "t": "data",
        "v": "4,179"
    }],
    [{
        "p": {
            "uk": "k2"
        },
        "t": "rowH",
        "v": "山西"
    }, {
        "p": {
            "fmt": "#.00",
            "raw": "34982.23000000001"
        },
        "t": "data",
        "v": "34982.23"
    }, {
        "p": {
            "fmt": "#,##0",
            "raw": "10422.0"
        },
        "t": "data",
        "v": "10,422"
    }],
    [{
        "p": {
            "uk": "k2"
        },
        "t": "rowH",
        "v": "陕西"
    }, {
        "p": {
            "fmt": "#.00",
            "raw": "14711.379999999994"
        },
        "t": "data",
        "v": "14711.38"
    }, {
        "p": {
            "fmt": "#,##0",
            "raw": "3938.0"
        },
        "t": "data",
        "v": "3,938"
    }],
    [{
        "p": {
            "uk": "k2"
        },
        "t": "rowH",
        "v": "上海"
    }, {
        "p": {
            "fmt": "#.00",
            "raw": "9255.079999999998"
        },
        "t": "data",
        "v": "9255.08"
    }, {
        "p": {
            "fmt": "#,##0",
            "raw": "2208.0"
        },
        "t": "data",
        "v": "2,208"
    }],
    [{
        "p": {
            "uk": "k2"
        },
        "t": "rowH",
        "v": "四川"
    }, {
        "p": {
            "fmt": "#.00",
            "raw": "7061.539999999998"
        },
        "t": "data",
        "v": "7061.54"
    }, {
        "p": {
            "fmt": "#,##0",
            "raw": "2295.0"
        },
        "t": "data",
        "v": "2,295"
    }],
    [{
        "p": {
            "uk": "k2"
        },
        "t": "rowH",
        "v": "天津"
    }, {
        "p": {
            "fmt": "#.00",
            "raw": "21947.819999999992"
        },
        "t": "data",
        "v": "21947.82"
    }, {
        "p": {
            "fmt": "#,##0",
            "raw": "7294.0"
        },
        "t": "data",
        "v": "7,294"
    }],
    [{
        "p": {
            "uk": "k2"
        },
        "t": "rowH",
        "v": "西藏"
    }, {
        "p": {
            "fmt": "#.00",
            "raw": "1598.23"
        },
        "t": "data",
        "v": "1598.23"
    }, {
        "p": {
            "fmt": "#,##0",
            "raw": "702.0"
        },
        "t": "data",
        "v": "702"
    }],
    [{
        "p": {
            "uk": "k2"
        },
        "t": "rowH",
        "v": "新疆"
    }, {
        "p": {
            "fmt": "#.00",
            "raw": "8451.229999999998"
        },
        "t": "data",
        "v": "8451.23"
    }, {
        "p": {
            "fmt": "#,##0",
            "raw": "1934.0"
        },
        "t": "data",
        "v": "1,934"
    }],
    [{
        "p": {
            "uk": "k2"
        },
        "t": "rowH",
        "v": "云南"
    }, {
        "p": {
            "fmt": "#.00",
            "raw": "2135.59"
        },
        "t": "data",
        "v": "2135.59"
    }, {
        "p": {
            "fmt": "#,##0",
            "raw": "573.0"
        },
        "t": "data",
        "v": "573"
    }],
    [{
        "p": {
            "uk": "k2"
        },
        "t": "rowH",
        "v": "浙江"
    }, {
        "p": {
            "fmt": "#.00",
            "raw": "63745.98000000003"
        },
        "t": "data",
        "v": "63745.98"
    }, {
        "p": {
            "fmt": "#,##0",
            "raw": "16682.0"
        },
        "t": "data",
        "v": "16,682"
    }],
    [{
        "p": {
            "uk": "k2"
        },
        "t": "rowH",
        "v": "重庆"
    }, {
        "p": {
            "fmt": "#.00",
            "raw": "5055.48"
        },
        "t": "data",
        "v": "5055.48"
    }, {
        "p": {
            "fmt": "#,##0",
            "raw": "1282.0"
        },
        "t": "data",
        "v": "1,282"
    }]
]
