[
    [
        {
            "p": {
                "name": "report_date"
            },
            "t": "rowH",
            "v": "日期"
        },
        {
            "p": {
                "name": "report_value"
            },
            "t": "colH",
            "v": "数值"
        }
    ],
    [
        {
            "p": {
                "name": "20141118"
            },
            "t": "rowH",
            "v": "20141118"
        },
        {
            "p": {
                "raw": 0.0023
            },
            "t": "data",
            "v": ".23%"
        }
    ],
    [
        {
            "p": {
                "name": "20141119"
            },
            "t": "rowH",
            "v": "20141119"
        },
        {
            "p": {
                "raw": 0.0016
            },
            "t": "data",
            "v": ".16%"
        }
    ],
    [
        {
            "p": {
                "name": "20141120"
            },
            "t": "rowH",
            "v": "20141120"
        },
        {
            "p": {
                "raw": 0.0030
            },
            "t": "data",
            "v": ".30%"
        }
    ],
    [
        {
            "p": {
                "name": "20141121"
            },
            "t": "rowH",
            "v": "20141121"
        },
        {
            "p": {
                "raw": 0.0019
            },
            "t": "data",
            "v": ".19%"
        }
    ],
    [
        {
            "p": {
                "name": "20141122"
            },
            "t": "rowH",
            "v": "20141122"
        },
        {
            "p": {
                "raw": 0.0020
            },
            "t": "data",
            "v": ".20%"
        }
    ],
    [
        {
            "p": {
                "name": "20141123"
            },
            "t": "rowH",
            "v": "20141123"
        },
        {
            "p": {
                "raw": 0.0008
            },
            "t": "data",
            "v": ".08%"
        }
    ]
]