[
    [{
        "p": {
            "dimGranularity": "REGION",
            "dimType": "GeographicDimension",
            "name": "area",
            "uk": "k1"
        },
        "t": "rowH",
        "v": "区域"
    }, {
        "p": {
            "aggType": "sum",
            "dimType": "measureCol",
            "name": "price",
            "uk": "k0"
        },
        "t": "colH",
        "v": "单价"
    }],
    [{
        "p": {
            "uk": "k1"
        },
        "t": "rowH",
        "v": "东北"
    }, {
        "p": {
            "raw": "92817.23000000005"
        },
        "t": "data",
        "v": "92817.23000000005"
    }],
    [{
        "p": {
            "uk": "k1"
        },
        "t": "rowH",
        "v": "华北"
    }, {
        "p": {
            "raw": "152504.51999999996"
        },
        "t": "data",
        "v": "152504.51999999996"
    }],
    [{
        "p": {
            "uk": "k1"
        },
        "t": "rowH",
        "v": "华东"
    }, {
        "p": {
            "raw": "154059.52"
        },
        "t": "data",
        "v": "154059.52"
    }],
    [{
        "p": {
            "uk": "k1"
        },
        "t": "rowH",
        "v": "华南"
    }, {
        "p": {
            "raw": "276524.52999999997"
        },
        "t": "data",
        "v": "276524.52999999997"
    }],
    [{
        "p": {
            "uk": "k1"
        },
        "t": "rowH",
        "v": "西北"
    }, {
        "p": {
            "raw": "57555.66000000001"
        },
        "t": "data",
        "v": "57555.66000000001"
    }],
    [{
        "p": {
            "uk": "k1"
        },
        "t": "rowH",
        "v": "西南"
    }, {
        "p": {
            "raw": "23842.629999999997"
        },
        "t": "data",
        "v": "23842.629999999997"
    }]
]
